[{"DATE":"2020-08-30T00:00:00.000Z","CO":1.37,"CO_max":1.42,"CO_min":1.32,"PM10":8.14,"PM10_max":12.91,"PM10_min":4.44,"WTEMP":25.75,"WTEMP_max":25.77,"WTEMP_min":25.74,"ACOND":31753.29,"ACOND_max":32015.45,"ACOND_min":31455.47,"SCOND":31303.83,"SCOND_max":31559.52,"SCOND_min":31013.28,"SAL":19.78,"SAL_max":19.96,"SAL_min":19.58,"TSOL":20.35,"TSOL_max":20.51,"TSOL_min":20.16,"PH":8.23,"PH_max":8.25,"PH_min":8.22,"ORP":252.21,"ORP_max":255.3,"ORP_min":246.33,"RDO":4.75,"RDO_max":4.95,"RDO_min":4.54,"TURB":6.52,"TURB_max":79.91,"TURB_min":1.43,"TSS":0.0,"TSS_max":0.0,"TSS_min":0.0,"STATUS":6,"TYPE":"previous","WS":"-","T":"-","WG":"-","WD":"-","RH":"-"},{"DATE":"2020-08-30T00:00:00.000Z","CO":1.38,"CO_max":1.44,"CO_min":1.33,"PM10":12.03,"PM10_max":16.4,"PM10_min":8.2,"WTEMP":25.59,"WTEMP_max":25.61,"WTEMP_min":25.58,"ACOND":31904.77,"ACOND_max":32178.47,"ACOND_min":31510.12,"SCOND":31548.85,"SCOND_max":31817.98,"SCOND_min":31160.1,"SAL":19.95,"SAL_max":20.14,"SAL_min":19.68,"TSOL":20.51,"TSOL_max":20.68,"TSOL_min":20.26,"PH":8.24,"PH_max":8.26,"PH_min":8.23,"ORP":252.95,"ORP_max":257.29,"ORP_min":242.42,"RDO":4.68,"RDO_max":4.94,"RDO_min":4.51,"TURB":6.06,"TURB_max":44.91,"TURB_min":1.3,"TSS":0.0,"TSS_max":0.0,"TSS_min":0.0,"STATUS":9,"TYPE":"previous","WS":"-","T":"-","WG":"-","WD":"-","RH":"-"},{"DATE":"2020-08-30T00:00:00.000Z","CO":1.46,"CO_max":1.53,"CO_min":1.41,"PM10":14.83,"PM10_max":22.38,"PM10_min":10.93,"WTEMP":25.63,"WTEMP_max":25.64,"WTEMP_min":25.61,"ACOND":31770.38,"ACOND_max":31980.32,"ACOND_min":31539.43,"SCOND":31393.75,"SCOND_max":31598.87,"SCOND_min":31171.32,"SAL":19.84,"SAL_max":19.98,"SAL_min":19.68,"TSOL":20.41,"TSOL_max":20.54,"TSOL_min":20.26,"PH":8.29,"PH_max":8.3,"PH_min":8.27,"ORP":250.1,"ORP_max":254.49,"ORP_min":241.48,"RDO":5.71,"RDO_max":5.92,"RDO_min":5.45,"TURB":3.11,"TURB_max":7.16,"TURB_min":1.04,"TSS":0.0,"TSS_max":0.0,"TSS_min":0.0,"STATUS":12,"TYPE":"previous","WS":"-","T":"-","WG":"-","WD":"-","RH":"-"},{"DATE":"2020-08-30T00:00:00.000Z","CO":1.6,"CO_max":1.66,"CO_min":1.53,"PM10":20.2,"PM10_max":35.17,"PM10_min":13.7,"WTEMP":25.92,"WTEMP_max":25.98,"WTEMP_min":25.87,"ACOND":31040.8,"ACOND_max":31265.13,"ACOND_min":30817.82,"SCOND":30507.22,"SCOND_max":30705.85,"SCOND_min":30307.32,"SAL":19.23,"SAL_max":19.36,"SAL_min":19.09,"TSOL":19.83,"TSOL_max":19.96,"TSOL_min":19.7,"PH":8.3,"PH_max":8.31,"PH_min":8.29,"ORP":250.39,"ORP_max":254.89,"ORP_min":241.31,"RDO":5.98,"RDO_max":6.15,"RDO_min":5.82,"TURB":3.43,"TURB_max":7.35,"TURB_min":1.18,"TSS":0.0,"TSS_max":0.0,"TSS_min":0.0,"STATUS":15,"TYPE":"previous","WS":"-","T":"-","WG":"-","WD":"-","RH":"-"},{"DATE":"2020-08-30T00:00:00.000Z","CO":1.74,"CO_max":1.8,"CO_min":1.66,"PM10":15.12,"PM10_max":25.7,"PM10_min":9.2,"WTEMP":25.98,"WTEMP_max":26.02,"WTEMP_min":25.94,"ACOND":31669.75,"ACOND_max":31932.12,"ACOND_min":31411.98,"SCOND":31088.72,"SCOND_max":31328.55,"SCOND_min":30851.57,"SAL":19.63,"SAL_max":19.8,"SAL_min":19.47,"TSOL":20.21,"TSOL_max":20.36,"TSOL_min":20.06,"PH":8.28,"PH_max":8.29,"PH_min":8.27,"ORP":243.81,"ORP_max":248.7,"ORP_min":232.64,"RDO":5.75,"RDO_max":5.93,"RDO_min":5.53,"TURB":3.06,"TURB_max":6.44,"TURB_min":0.86,"TSS":0.0,"TSS_max":0.0,"TSS_min":0.0,"STATUS":18,"TYPE":"previous","WS":"-","T":"-","WG":"-","WD":"-","RH":"-"},{"DATE":"2020-08-30T00:00:00.000Z","CO":1.71,"CO_max":1.82,"CO_min":1.63,"PM10":17.94,"PM10_max":42.46,"PM10_min":10.12,"WTEMP":26.05,"WTEMP_max":26.07,"WTEMP_min":26.03,"ACOND":32522.2,"ACOND_max":32613.1,"ACOND_min":32421.21,"SCOND":31882.92,"SCOND_max":31970.22,"SCOND_min":31790.91,"SAL":20.18,"SAL_max":20.25,"SAL_min":20.12,"TSOL":20.72,"TSOL_max":20.78,"TSOL_min":20.66,"PH":8.29,"PH_max":8.31,"PH_min":8.27,"ORP":253.41,"ORP_max":257.65,"ORP_min":245.02,"RDO":5.87,"RDO_max":6.1,"RDO_min":5.6,"TURB":4.11,"TURB_max":7.82,"TURB_min":1.54,"TSS":0.0,"TSS_max":0.0,"TSS_min":0.0,"STATUS":22,"TYPE":"previous","WS":"-","T":"-","WG":"-","WD":"-","RH":"-"},{"DATE":"2020-08-31T00:00:00.000Z","CO":1.42,"CO_max":1.5,"CO_min":1.36,"PM10":13.7,"PM10_max":21.21,"PM10_min":9.98,"WTEMP":25.79,"WTEMP_max":25.81,"WTEMP_min":25.78,"ACOND":31770.8,"ACOND_max":31997.01,"ACOND_min":31515.59,"SCOND":31296.47,"SCOND_max":31516.81,"SCOND_min":31046.75,"SAL":19.77,"SAL_max":19.93,"SAL_min":19.6,"TSOL":20.34,"TSOL_max":20.49,"TSOL_min":20.18,"PH":8.27,"PH_max":8.28,"PH_min":8.24,"ORP":252.06,"ORP_max":256.14,"ORP_min":244.93,"RDO":5.27,"RDO_max":5.54,"RDO_min":4.95,"TURB":15.52,"TURB_max":321.79,"TURB_min":1.83,"TSS":0.0,"TSS_max":0.0,"TSS_min":0.0,"STATUS":6,"TYPE":"previous","WS":"-","T":"-","WG":"-","WD":"-","RH":"-"},{"DATE":"2020-08-31T00:00:00.000Z","CO":1.37,"CO_max":1.42,"CO_min":1.31,"PM10":11.82,"PM10_max":15.47,"PM10_min":8.63,"WTEMP":25.67,"WTEMP_max":25.68,"WTEMP_min":25.66,"ACOND":32068.4,"ACOND_max":32243.03,"ACOND_min":31924.72,"SCOND":31663.27,"SCOND_max":31833.15,"SCOND_min":31523.65,"SAL":20.03,"SAL_max":20.15,"SAL_min":19.93,"TSOL":20.58,"TSOL_max":20.69,"TSOL_min":20.49,"PH":8.28,"PH_max":8.29,"PH_min":8.26,"ORP":254.41,"ORP_max":258.89,"ORP_min":244.39,"RDO":5.46,"RDO_max":5.71,"RDO_min":5.14,"TURB":5.84,"TURB_max":8.8,"TURB_min":1.98,"TSS":0.0,"TSS_max":0.0,"TSS_min":0.0,"STATUS":9,"TYPE":"previous","WS":"-","T":"-","WG":"-","WD":"-","RH":"-"},{"DATE":"2020-08-31T00:00:00.000Z","CO":1.51,"CO_max":1.56,"CO_min":1.46,"PM10":12.46,"PM10_max":30.77,"PM10_min":7.9,"WTEMP":25.75,"WTEMP_max":25.78,"WTEMP_min":25.72,"ACOND":32576.57,"ACOND_max":32609.92,"ACOND_min":32552.58,"SCOND":32118.45,"SCOND_max":32135.03,"SCOND_min":32104.43,"SAL":20.35,"SAL_max":20.36,"SAL_min":20.33,"TSOL":20.88,"TSOL_max":20.89,"TSOL_min":20.87,"PH":8.3,"PH_max":8.31,"PH_min":8.28,"ORP":255.16,"ORP_max":259.66,"ORP_min":247.68,"RDO":5.82,"RDO_max":5.98,"RDO_min":5.58,"TURB":7.99,"TURB_max":14.68,"TURB_min":3.3,"TSS":0.0,"TSS_max":0.0,"TSS_min":0.0,"STATUS":12,"TYPE":"previous","WS":"-","T":"-","WG":"-","WD":"-","RH":"-"},{"DATE":"2020-08-31T00:00:00.000Z","CO":1.72,"CO_max":1.84,"CO_min":1.65,"PM10":10.8,"PM10_max":16.1,"PM10_min":5.92,"WTEMP":26.21,"WTEMP_max":26.26,"WTEMP_min":26.17,"ACOND":32639.95,"ACOND_max":32843.62,"ACOND_min":32419.85,"SCOND":31902.35,"SCOND_max":32083.8,"SCOND_min":31702.08,"SAL":20.2,"SAL_max":20.33,"SAL_min":20.06,"TSOL":20.74,"TSOL_max":20.85,"TSOL_min":20.6,"PH":8.32,"PH_max":8.33,"PH_min":8.31,"ORP":256.34,"ORP_max":259.5,"ORP_min":252.44,"RDO":6.43,"RDO_max":6.56,"RDO_min":6.26,"TURB":5.12,"TURB_max":9.46,"TURB_min":1.93,"TSS":0.0,"TSS_max":0.0,"TSS_min":0.0,"STATUS":15,"TYPE":"previous","WS":"-","T":"-","WG":"-","WD":"-","RH":"-"},{"DATE":"2020-08-31T00:00:00.000Z","CO":1.77,"CO_max":1.84,"CO_min":1.71,"PM10":8.91,"PM10_max":13.12,"PM10_min":5.1,"WTEMP":26.17,"WTEMP_max":26.22,"WTEMP_min":26.12,"ACOND":31524.33,"ACOND_max":31609.38,"ACOND_min":31419.9,"SCOND":30838.45,"SCOND_max":30905.45,"SCOND_min":30752.97,"SAL":19.46,"SAL_max":19.5,"SAL_min":19.4,"TSOL":20.05,"TSOL_max":20.09,"TSOL_min":19.99,"PH":8.31,"PH_max":8.32,"PH_min":8.3,"ORP":249.77,"ORP_max":254.37,"ORP_min":238.08,"RDO":6.28,"RDO_max":6.5,"RDO_min":6.05,"TURB":3.91,"TURB_max":7.39,"TURB_min":1.44,"TSS":0.0,"TSS_max":0.0,"TSS_min":0.0,"STATUS":18,"TYPE":"previous","WS":"-","T":"-","WG":"-","WD":"-","RH":"-"},{"DATE":"2020-08-31T00:00:00.000Z","CO":1.7,"CO_max":1.77,"CO_min":1.63,"PM10":25.17,"PM10_max":39.54,"PM10_min":11.15,"WTEMP":26.09,"WTEMP_max":26.11,"WTEMP_min":26.08,"ACOND":32456.09,"ACOND_max":32608.84,"ACOND_min":32313.5,"SCOND":31795.86,"SCOND_max":31942.48,"SCOND_min":31658.96,"SAL":20.13,"SAL_max":20.23,"SAL_min":20.03,"TSOL":20.67,"TSOL_max":20.76,"TSOL_min":20.58,"PH":8.33,"PH_max":8.34,"PH_min":8.32,"ORP":256.9,"ORP_max":261.07,"ORP_min":246.08,"RDO":6.55,"RDO_max":6.68,"RDO_min":6.39,"TURB":7.37,"TURB_max":12.46,"TURB_min":3.43,"TSS":0.0,"TSS_max":0.0,"TSS_min":0.0,"STATUS":22,"TYPE":"previous","WS":"-","T":"-","WG":"-","WD":"-","RH":"-"},{"DATE":"2020-09-01T00:00:00.000Z","CO":1.43,"CO_max":1.49,"CO_min":1.38,"PM10":4.18,"PM10_max":12.37,"PM10_min":2.0,"WTEMP":25.9,"WTEMP_max":25.91,"WTEMP_min":25.89,"ACOND":32044.91,"ACOND_max":32181.03,"ACOND_min":31920.48,"SCOND":31503.03,"SCOND_max":31634.72,"SCOND_min":31383.42,"SAL":19.92,"SAL_max":20.01,"SAL_min":19.84,"TSOL":20.48,"TSOL_max":20.56,"TSOL_min":20.4,"PH":8.27,"PH_max":8.28,"PH_min":8.26,"ORP":256.11,"ORP_max":259.7,"ORP_min":247.91,"RDO":5.51,"RDO_max":5.71,"RDO_min":5.31,"TURB":14.31,"TURB_max":18.91,"TURB_min":6.75,"TSS":0.0,"TSS_max":0.0,"TSS_min":0.0,"STATUS":6,"TYPE":"previous","WS":"-","T":"-","WG":"-","WD":"-","RH":"-"},{"DATE":"2020-09-01T00:00:00.000Z","CO":1.38,"CO_max":1.43,"CO_min":1.32,"PM10":5.42,"PM10_max":9.5,"PM10_min":2.78,"WTEMP":25.81,"WTEMP_max":25.82,"WTEMP_min":25.8,"ACOND":32596.43,"ACOND_max":32637.52,"ACOND_min":32527.42,"SCOND":32098.53,"SCOND_max":32135.33,"SCOND_min":32032.58,"SAL":20.33,"SAL_max":20.36,"SAL_min":20.28,"TSOL":20.86,"TSOL_max":20.89,"TSOL_min":20.82,"PH":8.28,"PH_max":8.29,"PH_min":8.27,"ORP":259.45,"ORP_max":262.85,"ORP_min":252.85,"RDO":5.55,"RDO_max":5.74,"RDO_min":5.34,"TURB":16.23,"TURB_max":20.6,"TURB_min":9.36,"TSS":0.0,"TSS_max":0.0,"TSS_min":0.0,"STATUS":9,"TYPE":"previous","WS":"-","T":"-","WG":"-","WD":"-","RH":"-"},{"DATE":"2020-09-01T00:00:00.000Z","CO":1.52,"CO_max":1.62,"CO_min":1.46,"PM10":7.56,"PM10_max":14.22,"PM10_min":4.03,"WTEMP":26.01,"WTEMP_max":26.05,"WTEMP_min":25.97,"ACOND":32245.15,"ACOND_max":32382.48,"ACOND_min":32077.83,"SCOND":31636.3,"SCOND_max":31762.57,"SCOND_min":31482.53,"SAL":20.01,"SAL_max":20.1,"SAL_min":19.9,"TSOL":20.56,"TSOL_max":20.65,"TSOL_min":20.46,"PH":8.31,"PH_max":8.32,"PH_min":8.3,"ORP":259.06,"ORP_max":262.39,"ORP_min":251.93,"RDO":6.14,"RDO_max":6.27,"RDO_min":5.94,"TURB":10.06,"TURB_max":15.3,"TURB_min":2.9,"TSS":0.0,"TSS_max":0.0,"TSS_min":0.0,"STATUS":12,"TYPE":"previous","WS":"-","T":"-","WG":"-","WD":"-","RH":"-"},{"DATE":"2020-09-01T00:00:00.000Z","CO":1.61,"CO_max":1.68,"CO_min":1.55,"PM10":5.91,"PM10_max":11.45,"PM10_min":2.1,"WTEMP":26.46,"WTEMP_max":26.52,"WTEMP_min":26.36,"ACOND":31349.02,"ACOND_max":31465.45,"ACOND_min":31174.92,"SCOND":30500.62,"SCOND_max":30580.63,"SCOND_min":30349.53,"SAL":19.23,"SAL_max":19.28,"SAL_min":19.12,"TSOL":19.82,"TSOL_max":19.88,"TSOL_min":19.73,"PH":8.3,"PH_max":8.31,"PH_min":8.29,"ORP":254.51,"ORP_max":257.89,"ORP_min":245.46,"RDO":6.15,"RDO_max":6.33,"RDO_min":5.92,"TURB":10.76,"TURB_max":19.39,"TURB_min":3.67,"TSS":0.0,"TSS_max":0.0,"TSS_min":0.0,"STATUS":15,"TYPE":"previous","WS":"-","T":"-","WG":"-","WD":"-","RH":"-"},{"DATE":"2020-09-01T00:00:00.000Z","CO":1.69,"CO_max":1.75,"CO_min":1.64,"PM10":3.48,"PM10_max":9.32,"PM10_min":2.0,"WTEMP":26.36,"WTEMP_max":26.39,"WTEMP_min":26.33,"ACOND":31963.07,"ACOND_max":32260.35,"ACOND_min":31778.32,"SCOND":31152.93,"SCOND_max":31430.8,"SCOND_min":30982.28,"SAL":19.68,"SAL_max":19.87,"SAL_min":19.56,"TSOL":20.25,"TSOL_max":20.43,"TSOL_min":20.14,"PH":8.32,"PH_max":8.33,"PH_min":8.31,"ORP":250.12,"ORP_max":253.78,"ORP_min":238.88,"RDO":6.43,"RDO_max":6.56,"RDO_min":6.28,"TURB":7.86,"TURB_max":17.98,"TURB_min":1.57,"TSS":0.0,"TSS_max":0.0,"TSS_min":0.0,"STATUS":18,"TYPE":"previous","WS":"-","T":"-","WG":"-","WD":"-","RH":"-"},{"DATE":"2020-09-01T00:00:00.000Z","CO":1.6,"CO_max":1.68,"CO_min":1.53,"PM10":8.61,"PM10_max":19.19,"PM10_min":2.09,"WTEMP":26.2,"WTEMP_max":26.22,"WTEMP_min":26.18,"ACOND":32627.14,"ACOND_max":32706.8,"ACOND_min":32511.14,"SCOND":31895.75,"SCOND_max":31967.86,"SCOND_min":31790.72,"SAL":20.2,"SAL_max":20.25,"SAL_min":20.12,"TSOL":20.73,"TSOL_max":20.78,"TSOL_min":20.66,"PH":8.31,"PH_max":8.32,"PH_min":8.3,"ORP":253.55,"ORP_max":256.79,"ORP_min":245.07,"RDO":6.18,"RDO_max":6.32,"RDO_min":6.01,"TURB":7.9,"TURB_max":13.55,"TURB_min":2.47,"TSS":0.0,"TSS_max":0.0,"TSS_min":0.0,"STATUS":22,"TYPE":"previous","WS":"-","T":"-","WG":"-","WD":"-","RH":"-"},{"DATE":"2020-09-02T00:00:00.000Z","CO":1.43,"CO_max":1.48,"CO_min":1.38,"PM10":2.4,"PM10_max":3.97,"PM10_min":2.0,"WTEMP":26.12,"WTEMP_max":26.13,"WTEMP_min":26.11,"ACOND":32381.44,"ACOND_max":32530.01,"ACOND_min":32265.98,"SCOND":31704.52,"SCOND_max":31849.16,"SCOND_min":31593.09,"SAL":20.06,"SAL_max":20.16,"SAL_min":19.98,"TSOL":20.61,"TSOL_max":20.7,"TSOL_min":20.54,"PH":8.28,"PH_max":8.29,"PH_min":8.27,"ORP":255.88,"ORP_max":259.22,"ORP_min":245.92,"RDO":5.6,"RDO_max":5.77,"RDO_min":5.42,"TURB":5.15,"TURB_max":9.4,"TURB_min":1.61,"TSS":0.0,"TSS_max":0.0,"TSS_min":0.0,"STATUS":6,"TYPE":"previous","WS":"-","T":"-","WG":"-","WD":"-","RH":"-"},{"DATE":"2020-09-02T00:00:00.000Z","CO":1.42,"CO_max":1.48,"CO_min":1.35,"PM10":7.4,"PM10_max":13.23,"PM10_min":3.45,"WTEMP":26.07,"WTEMP_max":26.08,"WTEMP_min":26.07,"ACOND":31401.32,"ACOND_max":31698.97,"ACOND_min":31178.87,"SCOND":30770.05,"SCOND_max":31061.25,"SCOND_min":30553.93,"SAL":19.41,"SAL_max":19.61,"SAL_min":19.26,"TSOL":20.0,"TSOL_max":20.19,"TSOL_min":19.86,"PH":8.27,"PH_max":8.28,"PH_min":8.26,"ORP":251.3,"ORP_max":255.08,"ORP_min":239.56,"RDO":5.47,"RDO_max":5.6,"RDO_min":5.31,"TURB":4.65,"TURB_max":7.18,"TURB_min":1.28,"TSS":0.0,"TSS_max":0.0,"TSS_min":0.0,"STATUS":9,"TYPE":"previous","WS":"-","T":"-","WG":"-","WD":"-","RH":"-"},{"DATE":"2020-09-02T00:00:00.000Z","CO":1.54,"CO_max":1.64,"CO_min":1.48,"PM10":7.77,"PM10_max":13.78,"PM10_min":4.48,"WTEMP":26.15,"WTEMP_max":26.18,"WTEMP_min":26.13,"ACOND":32821.93,"ACOND_max":32842.28,"ACOND_min":32800.88,"SCOND":32113.35,"SCOND_max":32126.45,"SCOND_min":32100.68,"SAL":20.35,"SAL_max":20.36,"SAL_min":20.34,"TSOL":20.87,"TSOL_max":20.88,"TSOL_min":20.86,"PH":8.28,"PH_max":8.29,"PH_min":8.27,"ORP":252.05,"ORP_max":255.48,"ORP_min":242.2,"RDO":5.64,"RDO_max":5.76,"RDO_min":5.48,"TURB":4.53,"TURB_max":7.11,"TURB_min":1.68,"TSS":0.0,"TSS_max":0.0,"TSS_min":0.0,"STATUS":12,"TYPE":"previous","WS":"-","T":"-","WG":"-","WD":"-","RH":"-"},{"DATE":"2020-09-02T00:00:00.000Z","CO":1.55,"CO_max":1.6,"CO_min":1.5,"PM10":7.01,"PM10_max":18.5,"PM10_min":2.0,"WTEMP":26.37,"WTEMP_max":26.4,"WTEMP_min":26.35,"ACOND":32454.13,"ACOND_max":32617.17,"ACOND_min":32097.45,"SCOND":31624.65,"SCOND_max":31775.42,"SCOND_min":31282.85,"SAL":20.01,"SAL_max":20.11,"SAL_min":19.77,"TSOL":20.56,"TSOL_max":20.66,"TSOL_min":20.33,"PH":8.29,"PH_max":8.3,"PH_min":8.29,"ORP":253.97,"ORP_max":257.47,"ORP_min":243.67,"RDO":5.9,"RDO_max":5.98,"RDO_min":5.79,"TURB":3.8,"TURB_max":7.12,"TURB_min":1.2,"TSS":0.0,"TSS_max":0.0,"TSS_min":0.0,"STATUS":15,"TYPE":"previous","WS":"-","T":"-","WG":"-","WD":"-","RH":"-"},{"DATE":"2020-09-02T00:00:00.000Z","CO":1.63,"CO_max":1.68,"CO_min":1.56,"PM10":4.57,"PM10_max":10.8,"PM10_min":2.12,"WTEMP":26.45,"WTEMP_max":26.47,"WTEMP_min":26.42,"ACOND":31605.52,"ACOND_max":31936.92,"ACOND_min":31503.16,"SCOND":30754.84,"SCOND_max":31072.02,"SCOND_min":30666.92,"SAL":19.4,"SAL_max":19.62,"SAL_min":19.34,"TSOL":19.99,"TSOL_max":20.2,"TSOL_min":19.93,"PH":8.29,"PH_max":8.3,"PH_min":8.29,"ORP":250.73,"ORP_max":255.0,"ORP_min":237.42,"RDO":5.99,"RDO_max":6.08,"RDO_min":5.87,"TURB":2.56,"TURB_max":5.29,"TURB_min":1.38,"TSS":0.0,"TSS_max":0.0,"TSS_min":0.0,"STATUS":18,"TYPE":"previous","WS":"-","T":"-","WG":"-","WD":"-","RH":"-"},{"DATE":"2020-09-03T00:00:00.000Z","CO":"-","CO_max":"-","CO_min":"-","PM10":"-","PM10_max":"-","PM10_min":"-","WTEMP":"-","WTEMP_max":"-","WTEMP_min":"-","ACOND":"-","ACOND_max":"-","ACOND_min":"-","SCOND":"-","SCOND_max":"-","SCOND_min":"-","SAL":"-","SAL_max":"-","SAL_min":"-","TSOL":"-","TSOL_max":"-","TSOL_min":"-","PH":"-","PH_max":"-","PH_min":"-","ORP":"-","ORP_max":"-","ORP_min":"-","RDO":"-","RDO_max":"-","RDO_min":"-","TURB":"-","TURB_max":"-","TURB_min":"-","TSS":"-","TSS_max":"-","TSS_min":"-","STATUS":"21","TYPE":"today","WS":3.1,"T":22.5,"WG":4.4,"WD":351,"RH":62},{"DATE":"2020-09-04T00:00:00.000Z","CO":"-","CO_max":"-","CO_min":"-","PM10":"-","PM10_max":"-","PM10_min":"-","WTEMP":"-","WTEMP_max":"-","WTEMP_min":"-","ACOND":"-","ACOND_max":"-","ACOND_min":"-","SCOND":"-","SCOND_max":"-","SCOND_min":"-","SAL":"-","SAL_max":"-","SAL_min":"-","TSOL":"-","TSOL_max":"-","TSOL_min":"-","PH":"-","PH_max":"-","PH_min":"-","ORP":"-","ORP_max":"-","ORP_min":"-","RDO":"-","RDO_max":"-","RDO_min":"-","TURB":"-","TURB_max":"-","TURB_min":"-","TSS":"-","TSS_max":"-","TSS_min":"-","STATUS":"06","TYPE":"forecast","WS":5.1,"T":18.9,"WG":5.5,"WD":53,"RH":61},{"DATE":"2020-09-04T00:00:00.000Z","CO":"-","CO_max":"-","CO_min":"-","PM10":"-","PM10_max":"-","PM10_min":"-","WTEMP":"-","WTEMP_max":"-","WTEMP_min":"-","ACOND":"-","ACOND_max":"-","ACOND_min":"-","SCOND":"-","SCOND_max":"-","SCOND_min":"-","SAL":"-","SAL_max":"-","SAL_min":"-","TSOL":"-","TSOL_max":"-","TSOL_min":"-","PH":"-","PH_max":"-","PH_min":"-","ORP":"-","ORP_max":"-","ORP_min":"-","RDO":"-","RDO_max":"-","RDO_min":"-","TURB":"-","TURB_max":"-","TURB_min":"-","TSS":"-","TSS_max":"-","TSS_min":"-","STATUS":"09","TYPE":"forecast","WS":4,"T":22.3,"WG":5.2,"WD":44,"RH":48},{"DATE":"2020-09-04T00:00:00.000Z","CO":"-","CO_max":"-","CO_min":"-","PM10":"-","PM10_max":"-","PM10_min":"-","WTEMP":"-","WTEMP_max":"-","WTEMP_min":"-","ACOND":"-","ACOND_max":"-","ACOND_min":"-","SCOND":"-","SCOND_max":"-","SCOND_min":"-","SAL":"-","SAL_max":"-","SAL_min":"-","TSOL":"-","TSOL_max":"-","TSOL_min":"-","PH":"-","PH_max":"-","PH_min":"-","ORP":"-","ORP_max":"-","ORP_min":"-","RDO":"-","RDO_max":"-","RDO_min":"-","TURB":"-","TURB_max":"-","TURB_min":"-","TSS":"-","TSS_max":"-","TSS_min":"-","STATUS":"12","TYPE":"forecast","WS":7.5,"T":29,"WG":8.7,"WD":304,"RH":37},{"DATE":"2020-09-04T00:00:00.000Z","CO":"-","CO_max":"-","CO_min":"-","PM10":"-","PM10_max":"-","PM10_min":"-","WTEMP":"-","WTEMP_max":"-","WTEMP_min":"-","ACOND":"-","ACOND_max":"-","ACOND_min":"-","SCOND":"-","SCOND_max":"-","SCOND_min":"-","SAL":"-","SAL_max":"-","SAL_min":"-","TSOL":"-","TSOL_max":"-","TSOL_min":"-","PH":"-","PH_max":"-","PH_min":"-","ORP":"-","ORP_max":"-","ORP_min":"-","RDO":"-","RDO_max":"-","RDO_min":"-","TURB":"-","TURB_max":"-","TURB_min":"-","TSS":"-","TSS_max":"-","TSS_min":"-","STATUS":"15","TYPE":"forecast","WS":10.1,"T":29.6,"WG":12.9,"WD":305,"RH":44},{"DATE":"2020-09-04T00:00:00.000Z","CO":"-","CO_max":"-","CO_min":"-","PM10":"-","PM10_max":"-","PM10_min":"-","WTEMP":"-","WTEMP_max":"-","WTEMP_min":"-","ACOND":"-","ACOND_max":"-","ACOND_min":"-","SCOND":"-","SCOND_max":"-","SCOND_min":"-","SAL":"-","SAL_max":"-","SAL_min":"-","TSOL":"-","TSOL_max":"-","TSOL_min":"-","PH":"-","PH_max":"-","PH_min":"-","ORP":"-","ORP_max":"-","ORP_min":"-","RDO":"-","RDO_max":"-","RDO_min":"-","TURB":"-","TURB_max":"-","TURB_min":"-","TSS":"-","TSS_max":"-","TSS_min":"-","STATUS":"18","TYPE":"forecast","WS":8.2,"T":28,"WG":11.7,"WD":310,"RH":49},{"DATE":"2020-09-04T00:00:00.000Z","CO":"-","CO_max":"-","CO_min":"-","PM10":"-","PM10_max":"-","PM10_min":"-","WTEMP":"-","WTEMP_max":"-","WTEMP_min":"-","ACOND":"-","ACOND_max":"-","ACOND_min":"-","SCOND":"-","SCOND_max":"-","SCOND_min":"-","SAL":"-","SAL_max":"-","SAL_min":"-","TSOL":"-","TSOL_max":"-","TSOL_min":"-","PH":"-","PH_max":"-","PH_min":"-","ORP":"-","ORP_max":"-","ORP_min":"-","RDO":"-","RDO_max":"-","RDO_min":"-","TURB":"-","TURB_max":"-","TURB_min":"-","TSS":"-","TSS_max":"-","TSS_min":"-","STATUS":"21","TYPE":"forecast","WS":4.6,"T":23.4,"WG":6.2,"WD":9,"RH":63},{"DATE":"2020-09-05T00:00:00.000Z","CO":"-","CO_max":"-","CO_min":"-","PM10":"-","PM10_max":"-","PM10_min":"-","WTEMP":"-","WTEMP_max":"-","WTEMP_min":"-","ACOND":"-","ACOND_max":"-","ACOND_min":"-","SCOND":"-","SCOND_max":"-","SCOND_min":"-","SAL":"-","SAL_max":"-","SAL_min":"-","TSOL":"-","TSOL_max":"-","TSOL_min":"-","PH":"-","PH_max":"-","PH_min":"-","ORP":"-","ORP_max":"-","ORP_min":"-","RDO":"-","RDO_max":"-","RDO_min":"-","TURB":"-","TURB_max":"-","TURB_min":"-","TSS":"-","TSS_max":"-","TSS_min":"-","STATUS":"06","TYPE":"forecast","WS":5.7,"T":20.1,"WG":5.4,"WD":64,"RH":43},{"DATE":"2020-09-05T00:00:00.000Z","CO":"-","CO_max":"-","CO_min":"-","PM10":"-","PM10_max":"-","PM10_min":"-","WTEMP":"-","WTEMP_max":"-","WTEMP_min":"-","ACOND":"-","ACOND_max":"-","ACOND_min":"-","SCOND":"-","SCOND_max":"-","SCOND_min":"-","SAL":"-","SAL_max":"-","SAL_min":"-","TSOL":"-","TSOL_max":"-","TSOL_min":"-","PH":"-","PH_max":"-","PH_min":"-","ORP":"-","ORP_max":"-","ORP_min":"-","RDO":"-","RDO_max":"-","RDO_min":"-","TURB":"-","TURB_max":"-","TURB_min":"-","TSS":"-","TSS_max":"-","TSS_min":"-","STATUS":"09","TYPE":"forecast","WS":5.5,"T":23.3,"WG":5.5,"WD":64,"RH":36},{"DATE":"2020-09-05T00:00:00.000Z","CO":"-","CO_max":"-","CO_min":"-","PM10":"-","PM10_max":"-","PM10_min":"-","WTEMP":"-","WTEMP_max":"-","WTEMP_min":"-","ACOND":"-","ACOND_max":"-","ACOND_min":"-","SCOND":"-","SCOND_max":"-","SCOND_min":"-","SAL":"-","SAL_max":"-","SAL_min":"-","TSOL":"-","TSOL_max":"-","TSOL_min":"-","PH":"-","PH_max":"-","PH_min":"-","ORP":"-","ORP_max":"-","ORP_min":"-","RDO":"-","RDO_max":"-","RDO_min":"-","TURB":"-","TURB_max":"-","TURB_min":"-","TSS":"-","TSS_max":"-","TSS_min":"-","STATUS":"12","TYPE":"forecast","WS":4.2,"T":29.6,"WG":3.5,"WD":251,"RH":29},{"DATE":"2020-09-05T00:00:00.000Z","CO":"-","CO_max":"-","CO_min":"-","PM10":"-","PM10_max":"-","PM10_min":"-","WTEMP":"-","WTEMP_max":"-","WTEMP_min":"-","ACOND":"-","ACOND_max":"-","ACOND_min":"-","SCOND":"-","SCOND_max":"-","SCOND_min":"-","SAL":"-","SAL_max":"-","SAL_min":"-","TSOL":"-","TSOL_max":"-","TSOL_min":"-","PH":"-","PH_max":"-","PH_min":"-","ORP":"-","ORP_max":"-","ORP_min":"-","RDO":"-","RDO_max":"-","RDO_min":"-","TURB":"-","TURB_max":"-","TURB_min":"-","TSS":"-","TSS_max":"-","TSS_min":"-","STATUS":"15","TYPE":"forecast","WS":7,"T":28.1,"WG":7.7,"WD":259,"RH":40},{"DATE":"2020-09-05T00:00:00.000Z","CO":"-","CO_max":"-","CO_min":"-","PM10":"-","PM10_max":"-","PM10_min":"-","WTEMP":"-","WTEMP_max":"-","WTEMP_min":"-","ACOND":"-","ACOND_max":"-","ACOND_min":"-","SCOND":"-","SCOND_max":"-","SCOND_min":"-","SAL":"-","SAL_max":"-","SAL_min":"-","TSOL":"-","TSOL_max":"-","TSOL_min":"-","PH":"-","PH_max":"-","PH_min":"-","ORP":"-","ORP_max":"-","ORP_min":"-","RDO":"-","RDO_max":"-","RDO_min":"-","TURB":"-","TURB_max":"-","TURB_min":"-","TSS":"-","TSS_max":"-","TSS_min":"-","STATUS":"18","TYPE":"forecast","WS":5.8,"T":26.8,"WG":7.3,"WD":289,"RH":49},{"DATE":"2020-09-05T00:00:00.000Z","CO":"-","CO_max":"-","CO_min":"-","PM10":"-","PM10_max":"-","PM10_min":"-","WTEMP":"-","WTEMP_max":"-","WTEMP_min":"-","ACOND":"-","ACOND_max":"-","ACOND_min":"-","SCOND":"-","SCOND_max":"-","SCOND_min":"-","SAL":"-","SAL_max":"-","SAL_min":"-","TSOL":"-","TSOL_max":"-","TSOL_min":"-","PH":"-","PH_max":"-","PH_min":"-","ORP":"-","ORP_max":"-","ORP_min":"-","RDO":"-","RDO_max":"-","RDO_min":"-","TURB":"-","TURB_max":"-","TURB_min":"-","TSS":"-","TSS_max":"-","TSS_min":"-","STATUS":"21","TYPE":"forecast","WS":3.6,"T":22.2,"WG":5.2,"WD":356,"RH":68}]